{
  "id": "fcc6a4aa-faa1-49b7-8c35-e86d661b5522",
  "prevId": "00000000-0000-0000-0000-000000000000",
  "version": "7",
  "dialect": "postgresql",
  "tables": {
    "messaging.attachment": {
      "name": "attachment",
      "schema": "messaging",
      "columns": {
        "id": {
          "name": "id",
          "type": "uuid",
          "primaryKey": true,
          "notNull": true,
          "default": "gen_random_uuid()"
        },
        "tenant_id": {
          "name": "tenant_id",
          "type": "uuid",
          "primaryKey": false,
          "notNull": true
        },
        "message_id": {
          "name": "message_id",
          "type": "uuid",
          "primaryKey": false,
          "notNull": false
        },
        "message_direction": {
          "name": "message_direction",
          "type": "message_direction",
          "typeSchema": "messaging",
          "primaryKey": false,
          "notNull": true
        },
        "sha256": {
          "name": "sha256",
          "type": "text",
          "primaryKey": false,
          "notNull": true
        },
        "original_name": {
          "name": "original_name",
          "type": "text",
          "primaryKey": false,
          "notNull": true
        },
        "mime_type": {
          "name": "mime_type",
          "type": "text",
          "primaryKey": false,
          "notNull": true
        },
        "size_bytes": {
          "name": "size_bytes",
          "type": "integer",
          "primaryKey": false,
          "notNull": true
        },
        "storage_path": {
          "name": "storage_path",
          "type": "text",
          "primaryKey": false,
          "notNull": true
        },
        "uploaded_at": {
          "name": "uploaded_at",
          "type": "timestamp with time zone",
          "primaryKey": false,
          "notNull": true,
          "default": "now()"
        },
        "metadata": {
          "name": "metadata",
          "type": "jsonb",
          "primaryKey": false,
          "notNull": true,
          "default": "'{}'::jsonb"
        }
      },
      "indexes": {
        "attachment_tenant_sha256_idx": {
          "name": "attachment_tenant_sha256_idx",
          "columns": [
            {
              "expression": "tenant_id",
              "isExpression": false,
              "asc": true,
              "nulls": "last"
            },
            {
              "expression": "sha256",
              "isExpression": false,
              "asc": true,
              "nulls": "last"
            }
          ],
          "isUnique": false,
          "concurrently": false,
          "method": "btree",
          "with": {}
        },
        "attachment_tenant_dir_message_idx": {
          "name": "attachment_tenant_dir_message_idx",
          "columns": [
            {
              "expression": "tenant_id",
              "isExpression": false,
              "asc": true,
              "nulls": "last"
            },
            {
              "expression": "message_direction",
              "isExpression": false,
              "asc": true,
              "nulls": "last"
            },
            {
              "expression": "message_id",
              "isExpression": false,
              "asc": true,
              "nulls": "last"
            }
          ],
          "isUnique": false,
          "concurrently": false,
          "method": "btree",
          "with": {}
        },
        "attachment_tenant_message_sha256_uq": {
          "name": "attachment_tenant_message_sha256_uq",
          "columns": [
            {
              "expression": "tenant_id",
              "isExpression": false,
              "asc": true,
              "nulls": "last"
            },
            {
              "expression": "message_id",
              "isExpression": false,
              "asc": true,
              "nulls": "last"
            },
            {
              "expression": "sha256",
              "isExpression": false,
              "asc": true,
              "nulls": "last"
            }
          ],
          "isUnique": true,
          "concurrently": false,
          "method": "btree",
          "with": {}
        }
      },
      "foreignKeys": {},
      "compositePrimaryKeys": {},
      "uniqueConstraints": {},
      "policies": {},
      "checkConstraints": {},
      "isRLSEnabled": false
    },
    "messaging.channel_account": {
      "name": "channel_account",
      "schema": "messaging",
      "columns": {
        "id": {
          "name": "id",
          "type": "uuid",
          "primaryKey": true,
          "notNull": true,
          "default": "gen_random_uuid()"
        },
        "tenant_id": {
          "name": "tenant_id",
          "type": "uuid",
          "primaryKey": false,
          "notNull": true
        },
        "channel": {
          "name": "channel",
          "type": "channel",
          "typeSchema": "messaging",
          "primaryKey": false,
          "notNull": true
        },
        "address": {
          "name": "address",
          "type": "text",
          "primaryKey": false,
          "notNull": true
        },
        "display_name": {
          "name": "display_name",
          "type": "text",
          "primaryKey": false,
          "notNull": false
        },
        "channel_config": {
          "name": "channel_config",
          "type": "jsonb",
          "primaryKey": false,
          "notNull": true,
          "default": "'{}'::jsonb"
        },
        "secrets_ref": {
          "name": "secrets_ref",
          "type": "text",
          "primaryKey": false,
          "notNull": false
        },
        "is_active": {
          "name": "is_active",
          "type": "boolean",
          "primaryKey": false,
          "notNull": true,
          "default": true
        },
        "created_at": {
          "name": "created_at",
          "type": "timestamp with time zone",
          "primaryKey": false,
          "notNull": true,
          "default": "now()"
        },
        "updated_at": {
          "name": "updated_at",
          "type": "timestamp with time zone",
          "primaryKey": false,
          "notNull": true,
          "default": "now()"
        },
        "metadata": {
          "name": "metadata",
          "type": "jsonb",
          "primaryKey": false,
          "notNull": true,
          "default": "'{}'::jsonb"
        }
      },
      "indexes": {
        "channel_account_tenant_channel_address_uq": {
          "name": "channel_account_tenant_channel_address_uq",
          "columns": [
            {
              "expression": "tenant_id",
              "isExpression": false,
              "asc": true,
              "nulls": "last"
            },
            {
              "expression": "channel",
              "isExpression": false,
              "asc": true,
              "nulls": "last"
            },
            {
              "expression": "address",
              "isExpression": false,
              "asc": true,
              "nulls": "last"
            }
          ],
          "isUnique": true,
          "concurrently": false,
          "method": "btree",
          "with": {}
        }
      },
      "foreignKeys": {},
      "compositePrimaryKeys": {},
      "uniqueConstraints": {},
      "policies": {},
      "checkConstraints": {},
      "isRLSEnabled": false
    },
    "messaging.inbound_message": {
      "name": "inbound_message",
      "schema": "messaging",
      "columns": {
        "id": {
          "name": "id",
          "type": "uuid",
          "primaryKey": true,
          "notNull": true,
          "default": "gen_random_uuid()"
        },
        "tenant_id": {
          "name": "tenant_id",
          "type": "uuid",
          "primaryKey": false,
          "notNull": true
        },
        "channel_account_id": {
          "name": "channel_account_id",
          "type": "uuid",
          "primaryKey": false,
          "notNull": true
        },
        "thread_id": {
          "name": "thread_id",
          "type": "uuid",
          "primaryKey": false,
          "notNull": false
        },
        "external_message_id": {
          "name": "external_message_id",
          "type": "text",
          "primaryKey": false,
          "notNull": true
        },
        "from_identity": {
          "name": "from_identity",
          "type": "text",
          "primaryKey": false,
          "notNull": true
        },
        "to_identities": {
          "name": "to_identities",
          "type": "text[]",
          "primaryKey": false,
          "notNull": true,
          "default": "'{}'"
        },
        "subject": {
          "name": "subject",
          "type": "text",
          "primaryKey": false,
          "notNull": false
        },
        "body_plain": {
          "name": "body_plain",
          "type": "text",
          "primaryKey": false,
          "notNull": true
        },
        "body_html": {
          "name": "body_html",
          "type": "text",
          "primaryKey": false,
          "notNull": false
        },
        "received_at": {
          "name": "received_at",
          "type": "timestamp with time zone",
          "primaryKey": false,
          "notNull": true,
          "default": "now()"
        },
        "channel_payload": {
          "name": "channel_payload",
          "type": "jsonb",
          "primaryKey": false,
          "notNull": true,
          "default": "'{}'::jsonb"
        },
        "classification": {
          "name": "classification",
          "type": "text",
          "primaryKey": false,
          "notNull": false
        },
        "classified_at": {
          "name": "classified_at",
          "type": "timestamp with time zone",
          "primaryKey": false,
          "notNull": false
        },
        "vendor_id": {
          "name": "vendor_id",
          "type": "text",
          "primaryKey": false,
          "notNull": false
        },
        "purchase_order_id": {
          "name": "purchase_order_id",
          "type": "text",
          "primaryKey": false,
          "notNull": false
        },
        "metadata": {
          "name": "metadata",
          "type": "jsonb",
          "primaryKey": false,
          "notNull": true,
          "default": "'{}'::jsonb"
        }
      },
      "indexes": {
        "inbound_message_tenant_account_external_uq": {
          "name": "inbound_message_tenant_account_external_uq",
          "columns": [
            {
              "expression": "tenant_id",
              "isExpression": false,
              "asc": true,
              "nulls": "last"
            },
            {
              "expression": "channel_account_id",
              "isExpression": false,
              "asc": true,
              "nulls": "last"
            },
            {
              "expression": "external_message_id",
              "isExpression": false,
              "asc": true,
              "nulls": "last"
            }
          ],
          "isUnique": true,
          "concurrently": false,
          "method": "btree",
          "with": {}
        },
        "inbound_message_tenant_received_idx": {
          "name": "inbound_message_tenant_received_idx",
          "columns": [
            {
              "expression": "tenant_id",
              "isExpression": false,
              "asc": true,
              "nulls": "last"
            },
            {
              "expression": "received_at",
              "isExpression": false,
              "asc": false,
              "nulls": "last"
            }
          ],
          "isUnique": false,
          "concurrently": false,
          "method": "btree",
          "with": {}
        },
        "inbound_message_tenant_vendor_received_idx": {
          "name": "inbound_message_tenant_vendor_received_idx",
          "columns": [
            {
              "expression": "tenant_id",
              "isExpression": false,
              "asc": true,
              "nulls": "last"
            },
            {
              "expression": "vendor_id",
              "isExpression": false,
              "asc": true,
              "nulls": "last"
            },
            {
              "expression": "received_at",
              "isExpression": false,
              "asc": false,
              "nulls": "last"
            }
          ],
          "isUnique": false,
          "concurrently": false,
          "method": "btree",
          "with": {}
        },
        "inbound_message_tenant_purchase_order_received_idx": {
          "name": "inbound_message_tenant_purchase_order_received_idx",
          "columns": [
            {
              "expression": "tenant_id",
              "isExpression": false,
              "asc": true,
              "nulls": "last"
            },
            {
              "expression": "purchase_order_id",
              "isExpression": false,
              "asc": true,
              "nulls": "last"
            },
            {
              "expression": "received_at",
              "isExpression": false,
              "asc": false,
              "nulls": "last"
            }
          ],
          "isUnique": false,
          "concurrently": false,
          "method": "btree",
          "with": {}
        },
        "inbound_message_tenant_classification_idx": {
          "name": "inbound_message_tenant_classification_idx",
          "columns": [
            {
              "expression": "tenant_id",
              "isExpression": false,
              "asc": true,
              "nulls": "last"
            },
            {
              "expression": "classification",
              "isExpression": false,
              "asc": true,
              "nulls": "last"
            }
          ],
          "isUnique": false,
          "concurrently": false,
          "method": "btree",
          "with": {}
        }
      },
      "foreignKeys": {
        "inbound_message_channel_account_id_channel_account_id_fk": {
          "name": "inbound_message_channel_account_id_channel_account_id_fk",
          "tableFrom": "inbound_message",
          "tableTo": "channel_account",
          "schemaTo": "messaging",
          "columnsFrom": [
            "channel_account_id"
          ],
          "columnsTo": [
            "id"
          ],
          "onDelete": "no action",
          "onUpdate": "no action"
        },
        "inbound_message_thread_id_message_thread_id_fk": {
          "name": "inbound_message_thread_id_message_thread_id_fk",
          "tableFrom": "inbound_message",
          "tableTo": "message_thread",
          "schemaTo": "messaging",
          "columnsFrom": [
            "thread_id"
          ],
          "columnsTo": [
            "id"
          ],
          "onDelete": "no action",
          "onUpdate": "no action"
        }
      },
      "compositePrimaryKeys": {},
      "uniqueConstraints": {},
      "policies": {},
      "checkConstraints": {},
      "isRLSEnabled": false
    },
    "messaging.message_thread": {
      "name": "message_thread",
      "schema": "messaging",
      "columns": {
        "id": {
          "name": "id",
          "type": "uuid",
          "primaryKey": true,
          "notNull": true,
          "default": "gen_random_uuid()"
        },
        "tenant_id": {
          "name": "tenant_id",
          "type": "uuid",
          "primaryKey": false,
          "notNull": true
        },
        "channel": {
          "name": "channel",
          "type": "channel",
          "typeSchema": "messaging",
          "primaryKey": false,
          "notNull": true
        },
        "external_thread_id": {
          "name": "external_thread_id",
          "type": "text",
          "primaryKey": false,
          "notNull": true
        },
        "vendor_id": {
          "name": "vendor_id",
          "type": "text",
          "primaryKey": false,
          "notNull": false
        },
        "first_message_at": {
          "name": "first_message_at",
          "type": "timestamp with time zone",
          "primaryKey": false,
          "notNull": true,
          "default": "now()"
        },
        "last_message_at": {
          "name": "last_message_at",
          "type": "timestamp with time zone",
          "primaryKey": false,
          "notNull": true,
          "default": "now()"
        },
        "message_count": {
          "name": "message_count",
          "type": "integer",
          "primaryKey": false,
          "notNull": true,
          "default": 0
        },
        "metadata": {
          "name": "metadata",
          "type": "jsonb",
          "primaryKey": false,
          "notNull": true,
          "default": "'{}'::jsonb"
        }
      },
      "indexes": {
        "message_thread_tenant_channel_external_uq": {
          "name": "message_thread_tenant_channel_external_uq",
          "columns": [
            {
              "expression": "tenant_id",
              "isExpression": false,
              "asc": true,
              "nulls": "last"
            },
            {
              "expression": "channel",
              "isExpression": false,
              "asc": true,
              "nulls": "last"
            },
            {
              "expression": "external_thread_id",
              "isExpression": false,
              "asc": true,
              "nulls": "last"
            }
          ],
          "isUnique": true,
          "concurrently": false,
          "method": "btree",
          "with": {}
        },
        "message_thread_tenant_vendor_idx": {
          "name": "message_thread_tenant_vendor_idx",
          "columns": [
            {
              "expression": "tenant_id",
              "isExpression": false,
              "asc": true,
              "nulls": "last"
            },
            {
              "expression": "vendor_id",
              "isExpression": false,
              "asc": true,
              "nulls": "last"
            }
          ],
          "isUnique": false,
          "concurrently": false,
          "method": "btree",
          "with": {}
        }
      },
      "foreignKeys": {},
      "compositePrimaryKeys": {},
      "uniqueConstraints": {},
      "policies": {},
      "checkConstraints": {},
      "isRLSEnabled": false
    }
  },
  "enums": {
    "messaging.channel": {
      "name": "channel",
      "schema": "messaging",
      "values": [
        "email",
        "sms",
        "whatsapp",
        "slack",
        "voice",
        "manual",
        "photo"
      ]
    },
    "messaging.message_direction": {
      "name": "message_direction",
      "schema": "messaging",
      "values": [
        "inbound",
        "outbound"
      ]
    }
  },
  "schemas": {
    "messaging": "messaging"
  },
  "sequences": {},
  "roles": {},
  "policies": {},
  "views": {},
  "_meta": {
    "columns": {},
    "schemas": {},
    "tables": {}
  }
}